{
  "instrutores": [
    {
      "id": 0,
      "nome": "Bernardo",
      "sobrenome": "Rezende",
      "idade": 30,
      "email": "bernardo@cwi.com.br",
      "jaDeuAula": true,
      "aula": [
        "0",
        "2"
      ],
      "fotoUrl": "https://findallfaq.files.wordpress.com/2014/10/beeeeeeeeeeer.jpeg"
    },
    {
      "id": 1,
      "nome": "André",
      "sobrenome": "Nunes",
      "idade": 35,
      "email": "andre.nunes@cwi.com.br",
      "jaDeuAula": true,
      "aula": [
        "4"
      ],
      "fotoUrl": "https://pedrotavars.files.wordpress.com/2012/02/moneysmiley.png"
    },
    {
      "nome": "Lucas",
      "sobrenome": "Müller",
      "email": "lucas.smuller@hotmail.com",
      "idade": 17,
      "fotoUrl": "https://kokensupport.com/styles/simplicity_gray/theme/images/no_avatar.gif",
      "id": 2
    }
  ],
  "aulas": [
    {
      "id": 0,
      "nome": "OO"
    },
    {
      "id": 2,
      "nome": "Javascript"
    },
    {
      "id": 4,
      "nome": "SQL Server"
    },
    {
      "nome": "AngularJS",
      "id": 5
    },
    {
      "nome": "HTML e CSS",
      "id": 6
    },
    {
      "nome": "Oracle DB",
      "id": 7
    }
  ]
}